trading201/__init__.py
trading201-0.0.2.dist-info/METADATA
trading201-0.0.2.dist-info/WHEEL
trading201-0.0.2.dist-info/top_level.txt
trading201-0.0.2.dist-info/RECORD
